rclogvis/__init__.py
rclogvis/gps.py
rclogvis/plotting.py
rclogvis/version.py
rclogvis/apps/__init__.py
rclogvis/apps/combine_csv.py
rclogvis/apps/plot_data.py
rclogvis-0.2.1.dist-info/licenses/LICENSE
rclogvis-0.2.1.dist-info/METADATA
rclogvis-0.2.1.dist-info/WHEEL
rclogvis-0.2.1.dist-info/entry_points.txt
rclogvis-0.2.1.dist-info/top_level.txt
rclogvis-0.2.1.dist-info/zip-safe
rclogvis-0.2.1.dist-info/RECORD
