Metadata-Version: 2.4
Name: rclogvis
Version: 0.2.1
Summary: Telemetry log visualisation for EdgeTX radios.
Author-email: Fabian Jankowski <fjankowsk@gmail.com>
Maintainer-email: Fabian Jankowski <fjankowsk@gmail.com>
License-Expression: MIT
Project-URL: Homepage, https://github.com/fjankowsk/rclogvis
Project-URL: Issues, https://github.com/fjankowsk/rclogvis/issues
Project-URL: Repository, https://github.com/fjankowsk/rclogvis.git
Keywords: remote-control,uav,drone,logs,visualisation,data-analysis,edgetx
Classifier: Development Status :: 5 - Production/Stable
Classifier: Programming Language :: Python :: 3
Classifier: Operating System :: OS Independent
Requires-Python: >=3.9
License-File: LICENSE
Requires-Dist: gpxpy
Requires-Dist: matplotlib
Requires-Dist: numpy
Requires-Dist: pandas
Provides-Extra: develop
Requires-Dist: black; extra == "develop"
Requires-Dist: build; extra == "develop"
Requires-Dist: twine; extra == "develop"
Dynamic: license-file
